[
  {
    "class_name": "友情链接",
    "class_desc": "那些人，那些事",
    "link_list": [
            {
				"name": "小游", 
				"link": "https://xiaoyou66.com", 
				"avatar": "https://img.xiaoyou66.com/images/2020/01/14/nUDD.jpg", 
				"descr": "二次元技术宅"
			}, 
			{
				"name": "繁华如风的小站", 
				"link": "https://clover1420.top/", 
				"avatar": "https://fastly.jsdelivr.net/gh/clover1420/tc@main/image/2020/12/tx.png", 
				"descr": ""
			}, 
			{	
				"name": "itsNekoDeng", 
				"link": "https://dyfa.top/", 
				"avatar": "https://nekodeng.gitee.io/medias/avatar.jpg", 
				"descr": "十万伏特皮卡丘，梦想是世界和平，想要发光发热"
			}, 
			{	
				"name": "阡陌的小窝", 
				"link": "https://www.weiaini.xyz", 
				"avatar": "https://www.weiaini.xyz/avatar.png", 
				"descr": "记录技术与人生感想的小窝" 
			}, 
			{	
				"name": "温锦瑜的博客", 
				"link": "https://www.wenjinyu.me/", 
				"avatar": "https://fastly.jsdelivr.net/gh/sakurasep/images_01@1.1/avatar/wenjinyu.png", 
				"descr": "先想想为什么，再考虑怎么做" 
			}, 
			{	
				"name": "Torrk's Blog", 
				"link": "https://conimi.com", 
				"avatar": "https://xingqiu-tuchuang-1256524210.cos.ap-shanghai.myqcloud.com/5199/Friends_Shot/20220523180818.png", 
				"descr": "记录，成为更好的自己。" 
			}, 
			{	
				"name": "迷鹿", 
				"link": "https://www.lostfawn.cn", 
				"avatar": "https://fastly.jsdelivr.net/gh/jack-bin183/cdn@1.7/img/custom/avatar.png", 
				"descr": "等待也是约会的一部分嘛"
			}, 
			{	
				"name": "MJ's Blog", 
				"link": "https://blog.justlovesmile.top", 
				"avatar": "https://fastly.jsdelivr.net/gh/Justlovesmile/CDN/image/logo.jpg", 
				"descr": "醒亦念卿，梦亦念卿" 
			}, 
			{	
				"name": "云玩家", 
				"link": "https://yunist.cn", 
				"avatar": "https://fastly.jsdelivr.net/gh/cnyist/blog/img/avatar.svg", 
				"descr": "虽于果壳内, 我亦无限王." 
			}, 
			{	
				"name": "李本伟的博客", 
				"link": "https://blog.libw.cc", 
				"avatar": "https://fastly.jsdelivr.net/gh/Li-Zi-stu/Pictures@1.6/%E5%A4%B4%E5%83%8F/%E5%A4%B4%E5%83%8F.png", 
				"descr": "科学，是一种信仰，更是一种力量！" 
			}, 
			{
				"name": "GOOPHER's Blog", 
				"link": "https://goopher.tk", 
				"avatar": "https://fastly.jsdelivr.net/gh/Goopher97/tuchuang@master/img/18DAD281896408F73F4EF594111BECA2.jpg", 
				"descr": "记录折腾的生活。" 
			}, 
			{	
				"name": "鲸一", 
				"link": "https://www.saroin.com/", 
				"avatar": "https://fastly.jsdelivr.net/gh/sakurasep/images_01@1.1/avatar/saroin.jpg", 
				"descr": "希望是件美好的事，也许是世间最美好的东西，而美好的事物永不消逝!"
			}, 
			{	
				"name": "心月云", 
				"link": "https://wch666.com", 
				"avatar": "https://wch666.com/head.png", 
				"descr": "永远年轻，永远热泪盈眶" 
			}, 
			{	
				"name": "徐艺扬的博客", 
				"link": "https://xuyiyang.com.cn/", 
				"avatar": "https://fastly.jsdelivr.net/gh/sakurasep/images_01@1.1/avatar/xuyiyang.jpg", 
				"descr": "分享有趣、有用的东西。"
			}, 
			{	
				"name": "小浣熊的技术小站", 
				"link": "https://nimitiz.cn/", 
				"avatar": "https://ftp.bmp.ovh/imgs/2020/08/af2963980918097c.jpg ", 
				"descr": "生命不息，折腾不止" 
			}, 
			{
				"name": "xuzf的呓语", 
				"link": "https://blog.xuzf.top/", 
				"avatar": "https://i.loli.net/2020/04/05/PoYEF6cWH5klRpA.png", 
				"descr": "Believers on the open source pilgrimage"
			}, 
			{	
				"name": "pei你看雪", 
				"link": "https://pnkx.top/", 
				"avatar": "https://xingqiu-tuchuang-1256524210.cos.ap-shanghai.myqcloud.com/5199/px.jpg", 
				"descr": "陪伴是最长情的告白"
			}, 
			{	
				"name": "Throwable", 
				"avatar": "https://throwable-blog-1256189093.cos.ap-guangzhou.myqcloud.com/mine/doge_avatar.jpg", 
				"link": "https://www.throwx.cn", 
				"descr": "Java后端开发、基础架构、并发编程"
			}, 
			{	
				"name": "九月的生活", 
				"link": "https://blog.sakurasep.club/", 
				"avatar": "https://fastly.jsdelivr.net/gh/sakurasep/images@1.4/important/touxiang.jpg", 
				"descr": "New Dream New Start"
			}
    ]
  },
  {
    "class_name": "网站",
    "class_desc": "值得推荐的网站",
    "link_list": [
      {
        "name": "九月的生活",
        "link": "https://blog.sakurasep.club/",
        "avatar": "https://xingqiu-tuchuang-1256524210.cos.ap-shanghai.myqcloud.com/5199/touxiang.jpg",
        "descr": "分享自己的生活站"
      },
      {
        "name": "Ven_殃雾",
        "link": "https://youngfog.cn/",
        "avatar": "https://xingqiu-tuchuang-1256524210.cos.ap-shanghai.myqcloud.com/5199/wallpaper/ven.jpg",
        "descr": "只做灵感的信徒，秉持热爱的信条"
      }
    ]
  }
]